dj_email_url.py
dj_email_url-1.0.4.dist-info/LICENSE
dj_email_url-1.0.4.dist-info/METADATA
dj_email_url-1.0.4.dist-info/WHEEL
dj_email_url-1.0.4.dist-info/top_level.txt
dj_email_url-1.0.4.dist-info/RECORD
